mydata_did/__init__.py
mydata_did/definition.py
mydata_did/patched_protocols/__init__.py
mydata_did/patched_protocols/issue_credential/__init__.py
mydata_did/patched_protocols/issue_credential/definition.py
mydata_did/patched_protocols/issue_credential/v1_0/__init__.py
mydata_did/patched_protocols/issue_credential/v1_0/handlers/__init__.py
mydata_did/patched_protocols/issue_credential/v1_0/handlers/credential_ack_handler.py
mydata_did/patched_protocols/issue_credential/v1_0/handlers/credential_issue_handler.py
mydata_did/patched_protocols/issue_credential/v1_0/handlers/credential_offer_handler.py
mydata_did/patched_protocols/issue_credential/v1_0/handlers/credential_proposal_handler.py
mydata_did/patched_protocols/issue_credential/v1_0/handlers/credential_request_handler.py
mydata_did/patched_protocols/issue_credential/v1_0/manager.py
mydata_did/patched_protocols/issue_credential/v1_0/message_types.py
mydata_did/patched_protocols/issue_credential/v1_0/messages/__init__.py
mydata_did/patched_protocols/issue_credential/v1_0/messages/credential_ack.py
mydata_did/patched_protocols/issue_credential/v1_0/messages/credential_issue.py
mydata_did/patched_protocols/issue_credential/v1_0/messages/credential_offer.py
mydata_did/patched_protocols/issue_credential/v1_0/messages/credential_proposal.py
mydata_did/patched_protocols/issue_credential/v1_0/messages/credential_request.py
mydata_did/patched_protocols/issue_credential/v1_0/messages/inner/__init__.py
mydata_did/patched_protocols/issue_credential/v1_0/messages/inner/credential_preview.py
mydata_did/patched_protocols/issue_credential/v1_0/models/__init__.py
mydata_did/patched_protocols/issue_credential/v1_0/models/credential_exchange.py
mydata_did/patched_protocols/issue_credential/v1_0/routes.py
mydata_did/patched_protocols/present_proof/__init__.py
mydata_did/patched_protocols/present_proof/definition.py
mydata_did/patched_protocols/present_proof/v1_0/__init__.py
acapy_mydata_did_protocol-0.1.15.dist-info/LICENSE
acapy_mydata_did_protocol-0.1.15.dist-info/WHEEL
acapy_mydata_did_protocol-0.1.15.dist-info/METADATA
acapy_mydata_did_protocol-0.1.15.dist-info/RECORD
